django_opensearch_dsl_signals/apps.py
django_opensearch_dsl_signals/signals.py
django_opensearch_dsl_signals-0.0.2.dist-info/METADATA
django_opensearch_dsl_signals-0.0.2.dist-info/WHEEL
django_opensearch_dsl_signals-0.0.2.dist-info/RECORD
