Metadata-Version: 2.1
Name: django-opensearch-dsl-signals
Version: 0.0.2
Summary: Extension to django opensearch dsl with improved signals
License: MIT
Author: Bart Machielsen
Author-email: bartmachielsen@gmail.com
Requires-Python: >=3.7,<4.0
Classifier: License :: OSI Approved :: MIT License
Classifier: Programming Language :: Python :: 3
Classifier: Programming Language :: Python :: 3.7
Classifier: Programming Language :: Python :: 3.8
Classifier: Programming Language :: Python :: 3.9
Classifier: Programming Language :: Python :: 3.10
Classifier: Programming Language :: Python :: 3.11
Requires-Dist: PyYAML (>=5.4.1,<6.0.0)
Requires-Dist: boto3 (>=1.20.0,<2.0.0)
Requires-Dist: colorama (>=0.4.4,<0.5.0)
Requires-Dist: deepmerge (>=0.3.0,<0.4.0)
Requires-Dist: pydantic (>=1.9.0,<2.0.0)
Requires-Dist: structlog (>=21.5.0,<22.0.0)
Requires-Dist: tqdm (>=4.65.0,<5.0.0)
